cubiomespi/__init__.py
cubiomespi/cubiomes.py
cubiomespi/lib/compile.txt
cubiomespi/lib/lib.dll
cubiomespi/lib/newlib.c
cubiomespi-1.0.dist-info/METADATA
cubiomespi-1.0.dist-info/WHEEL
cubiomespi-1.0.dist-info/top_level.txt
cubiomespi-1.0.dist-info/RECORD
